Metadata-Version: 1.0
Name: dist-trial
Version: 1.0
Summary: Gaussian and Binomial distributions
Home-page: UNKNOWN
Author: Ilham Naharudinsyah
Author-email: ilham.naharudinsyah@gmail.com
License: UNKNOWN
Platform: UNKNOWN
